flytezen/__init__.py
flytezen/__main__.py
flytezen/cli/__init__.py
flytezen/cli/execute.py
flytezen/cli/execution_config.py
flytezen/cli/execution_utils.py
flytezen/configuration.py
flytezen/constants.py
flytezen/logging.py
flytezen/workflows/__init__.py
flytezen/workflows/example.py
flytezen/workflows/lrwine.py
flytezen-1.0.3.dist-info/LICENSE
flytezen-1.0.3.dist-info/METADATA
flytezen-1.0.3.dist-info/WHEEL
flytezen-1.0.3.dist-info/entry_points.txt
flytezen-1.0.3.dist-info/RECORD
