Metadata-Version: 2.1
Name: flytezen
Version: 1.0.3
Summary: Library for benchmarking the impact of transcript count type stratification on trajectory inference.
Home-page: https://sciexp.github.io/flytezen/
License: AGPL-3.0-only
Author: flytezen team
Requires-Python: ==3.10.13
Classifier: Development Status :: 2 - Pre-Alpha
Classifier: Intended Audience :: Developers
Classifier: License :: OSI Approved :: GNU Affero General Public License v3
Classifier: Natural Language :: English
Classifier: Programming Language :: Python :: 3
Classifier: Programming Language :: Python :: 3.10
Classifier: Programming Language :: Python :: 3.9
Provides-Extra: dev
Provides-Extra: docs
Provides-Extra: lint
Provides-Extra: test
Requires-Dist: black[jupyter] (==23.11.0) ; extra == "lint" or extra == "dev"
Requires-Dist: dataclasses-json (==0.5.9)
Requires-Dist: dulwich (==0.21.7)
Requires-Dist: flytekit (==1.10.2)
Requires-Dist: fsspec (==2023.9.2)
Requires-Dist: hydra-joblib-launcher (==1.2.0)
Requires-Dist: hydra-zen (==0.11.0)
Requires-Dist: jupyter_contrib_nbextensions (==0.7.0) ; extra == "docs" or extra == "dev"
Requires-Dist: jupyterlab (==4.0.9) ; extra == "docs"
Requires-Dist: jupytext (==1.16.0) ; extra == "docs" or extra == "dev"
Requires-Dist: mashumaro (==3.10)
Requires-Dist: mkdocs-jupyter (==0.24.6) ; extra == "docs" or extra == "dev"
Requires-Dist: mkdocs-material (==9.4.14) ; extra == "docs" or extra == "dev"
Requires-Dist: mkdocstrings (==0.24.0) ; extra == "docs" or extra == "dev"
Requires-Dist: mkdocstrings-python (==1.7.5)
Requires-Dist: mypy (==1.7.1) ; extra == "lint" or extra == "dev"
Requires-Dist: notebook (==6.4.13) ; extra == "docs" or extra == "dev"
Requires-Dist: pandas (==1.5.3)
Requires-Dist: plumbum (==1.8.2)
Requires-Dist: poethepoet (==0.24.4) ; extra == "test"
Requires-Dist: protobuf (==4.24.4)
Requires-Dist: pyarrow (==14.0.2)
Requires-Dist: pyperclip (==1.8.2)
Requires-Dist: pyright (==1.1.336) ; extra == "lint" or extra == "dev"
Requires-Dist: pytest (==7.4.3) ; extra == "test" or extra == "dev"
Requires-Dist: pytest-asyncio (==0.21.1) ; extra == "test" or extra == "dev"
Requires-Dist: pytest-cov (==4.1.0) ; extra == "test" or extra == "dev"
Requires-Dist: python-dotenv (==1.0.0)
Requires-Dist: rich (==13.6.0)
Requires-Dist: ruff (==0.1.5) ; extra == "lint" or extra == "dev"
Requires-Dist: scikit-learn (==1.3.2)
Requires-Dist: scipy (==1.10.1)
Requires-Dist: xdoctest (==1.1.2) ; extra == "test" or extra == "dev"
Project-URL: Changelog, https://github.com/sciexp/flytezen/releases
Project-URL: Documentation, https://sciexp.github.io/flytezen/
Project-URL: Repository, https://github.com/sciexp/flytezen
